proscan_log_api/__init__.py
proscan_log_api/examples.py
proscan_log_api/pass_log_client.py
proscan_log_api/slow_control_client.py
proscan_log_api/tcs_trace_client.py
proscan_log_api/utils.py
proscan_log_api-1.2.5.dist-info/LICENSE
proscan_log_api-1.2.5.dist-info/WHEEL
proscan_log_api-1.2.5.dist-info/METADATA
proscan_log_api-1.2.5.dist-info/RECORD
