Metadata-Version: 2.1
Name: proscan-log-api
Version: 1.2.5
Summary: Log API for PSI's PROSCAN
Author: Niklas Laufkoetter
Author-email: niklas.laufkoetter@psi.ch
Requires-Python: >=3.8,<4.0
Classifier: Programming Language :: Python :: 3
Classifier: Programming Language :: Python :: 3.8
Classifier: Programming Language :: Python :: 3.9
Classifier: Programming Language :: Python :: 3.10
Classifier: Programming Language :: Python :: 3.11
